{
  "discord": {
    "sha256": "0pq2ip51spbc2pqy816ggl4a00mf0nd2dxcv7qi03a052h2g5ljq",
    "url": "https://stable.dl2.discordapp.net/apps/linux/0.0.103/discord-0.0.103.tar.gz",
    "version": "0.0.103"
  },
  "discord-canary": {
    "sha256": "168s3ycj55c5n1fl92m3cizjkvcl3bbp41pjypy81xj830ka2fcl",
    "url": "https://canary.dl2.discordapp.net/apps/linux/0.0.730/discord-canary-0.0.730.tar.gz",
    "version": "0.0.730"
  },
  "discord-ptb": {
    "sha256": "0fyaw6ynx9fli90yihkf4q7799w048p5yl5p7fvvqfg5gz0dw234",
    "url": "https://ptb.dl2.discordapp.net/apps/linux/0.0.154/discord-ptb-0.0.154.tar.gz",
    "version": "0.0.154"
  }
}
