{
  "discord": {
    "sha256": "0b04b3af844y594974blyxds5cs71r9fwzndasvzl67hsz5jc5sq",
    "url": "https://dl.discordapp.net/apps/linux/0.0.25/discord-0.0.25.tar.gz",
    "version": "0.0.25"
  },
  "discord-canary": {
    "sha256": "1yj1l16kf5c556rqrb1sfkw3qk21xaryv0dpcpjdzdxlbfkq66zj",
    "url": "https://dl-canary.discordapp.net/apps/linux/0.0.150/discord-canary-0.0.150.tar.gz",
    "version": "0.0.150"
  },
  "discord-ptb": {
    "sha256": "1a9rr72xahfck9d5hc7k5cyzkfi75w3h5mvfl1mzj6qp15g9j602",
    "url": "https://dl-ptb.discordapp.net/apps/linux/0.0.41/discord-ptb-0.0.41.tar.gz",
    "version": "0.0.41"
  }
}
