{
  "discord": {
    "sha256": "1an0si1dmyxh1scw4sg3n2626vqdvmgpk6yx871nqqjg8bs5gm9a",
    "url": "https://dl.discordapp.net/apps/linux/0.0.63/discord-0.0.63.tar.gz",
    "version": "0.0.63"
  },
  "discord-canary": {
    "sha256": "0qk4xfvj91zn806d5q50mkgvlpr08vb96jir7an169xgl130bva5",
    "url": "https://dl-canary.discordapp.net/apps/linux/0.0.466/discord-canary-0.0.466.tar.gz",
    "version": "0.0.466"
  },
  "discord-ptb": {
    "sha256": "1k3v8d5zvkdrrn00spmrmpcif4vzhmdrya7lgx9p02jiwsp7k738",
    "url": "https://dl-ptb.discordapp.net/apps/linux/0.0.98/discord-ptb-0.0.98.tar.gz",
    "version": "0.0.98"
  }
}
