{
  "discord": {
    "sha256": "0cwbp5j2h5afbcbq3xs5pc0ywgnci2454p5yc8bm2kyykc0msmyv",
    "url": "https://stable.dl2.discordapp.net/apps/linux/0.0.124/discord-0.0.124.tar.gz",
    "version": "0.0.124"
  },
  "discord-canary": {
    "sha256": "1xrdlpavq58wjff7f9v22wpvnia7lnbw3zln7b4y1cix6yiyp7nm",
    "url": "https://canary.dl2.discordapp.net/apps/linux/0.0.867/discord-canary-0.0.867.tar.gz",
    "version": "0.0.867"
  },
  "discord-ptb": {
    "sha256": "118rrj6lk5slx88jxcp8f7kgi865bbs84p2lidnxs51kw4gs3r28",
    "url": "https://ptb.dl2.discordapp.net/apps/linux/0.0.176/discord-ptb-0.0.176.tar.gz",
    "version": "0.0.176"
  }
}
