{
  "discord": {
    "sha256": "05a56fiq53h93y3nwb4g3h7ip4843iyw0mm5zszx64d8rv3fa2r0",
    "url": "https://stable.dl2.discordapp.net/apps/linux/0.0.72/discord-0.0.72.tar.gz",
    "version": "0.0.72"
  },
  "discord-canary": {
    "sha256": "01jh7f2rr2wbh5njnl5ff0n6sii39cs2ljpsl1s2m6xj43zxii84",
    "url": "https://canary.dl2.discordapp.net/apps/linux/0.0.506/discord-canary-0.0.506.tar.gz",
    "version": "0.0.506"
  },
  "discord-ptb": {
    "sha256": "0i6s67pkxv4h53pivxm3ynv56r4rq35lzssfg05a45zyncm1b4n0",
    "url": "https://ptb.dl2.discordapp.net/apps/linux/0.0.112/discord-ptb-0.0.112.tar.gz",
    "version": "0.0.112"
  }
}
