{
  "discord": {
    "sha256": "1cs5qzmfv9sbf7xcxpi4dgrnd4iwcwiw5c3476nkjd4i2752j6ml",
    "url": "https://dl.discordapp.net/apps/linux/0.0.64/discord-0.0.64.tar.gz",
    "version": "0.0.64"
  },
  "discord-canary": {
    "sha256": "0nlgschp6j72injk6bdrgwl0csn5qhlsgd1ilrc781ykyzhli13n",
    "url": "https://dl-canary.discordapp.net/apps/linux/0.0.474/discord-canary-0.0.474.tar.gz",
    "version": "0.0.474"
  },
  "discord-ptb": {
    "sha256": "1zrjdi58jq78sf0p4mmhs1ib49j0y4bd9g5dlhqn28qya2x1v4ps",
    "url": "https://dl-ptb.discordapp.net/apps/linux/0.0.100/discord-ptb-0.0.100.tar.gz",
    "version": "0.0.100"
  }
}
